xmds2tools/__init__.py
xmds2tools/bessel.py
xmds2tools/reader.py
xmds2tools-1.0.1.dist-info/LICENSE
xmds2tools-1.0.1.dist-info/METADATA
xmds2tools-1.0.1.dist-info/WHEEL
xmds2tools-1.0.1.dist-info/top_level.txt
xmds2tools-1.0.1.dist-info/RECORD
