Metadata-Version: 2.1
Name: xmds2tools
Version: 1.0.1
Summary: Tools to read .hdf5 and .xsil files generated using XMDS2 and functions to implement Bessel transformations and Bessel quadrature integration
Author-email: Craig Chisholm <craig.chisholm@protonmail.com>
License: MIT License
Project-URL: Homepage, https://github.com/CSChisholm/xmds2-tools
Keywords: XMDS2,HDF5,Bessel
Classifier: License :: OSI Approved :: MIT License
Classifier: Programming Language :: Python
Classifier: Programming Language :: Python :: 3
Requires-Python: >=3.5
License-File: LICENSE
Requires-Dist: h5py
Requires-Dist: numpy
Requires-Dist: scipy (>=1.7.3)
Requires-Dist: et-xmlfile (>=1.0.1)
